[
  {
    "name":           ["states", "state"],
    "nexts":          [],
    "start_children": [["names", "0"]],
    "children":       [],
    "function_name":  "returnTrue",
    "data":           {},
    "parents":        [["root", "0"]]
  },
  {           
    "name":           ["prev_prev_indent"],
    "nexts":          [],
    "start_children": [],
    "children":       [],
    "function_name":  "returnTrue",
    "data":           {"int": "0"},
    "parents":        []
  },
  {           
    "name":           ["prev_indent"],
    "nexts":          [],
    "start_children": [],
    "children":       [],
    "function_name":  "returnTrue",
    "data":           {"int": "0"},
    "parents":        []
  },
  {
    "name":           ["prev_word"],
    "nexts":          [],
    "start_children": [],
    "children":       [],
    "function_name":  "returnTrue",
    "data":           {"char*":"root"},
    "parents":        []
  },
  {
    "name":           ["current_word"],
    "nexts":          [],
    "start_children": [],
    "children":       [],
    "function_name":  "returnTrue",
    "data":           {"char*":""},
    "parents":        []
  },
  {
    "name":           ["next_indent"],
    "nexts":          [],
    "start_children": [],
    "children":       [],
    "function_name":  "returnTrue",
    "data":           {"char*": "0"},
    "parents":        []
  },
  {
    "name":           ["level_indent_stack"],
    "nexts":          [],
    "start_children": [["level_number", "0"],
                       ["state_number", "0"],
                       ["indent_number", "0"],
                       ["max_stack_index"]],
    "children":        [],
    "function_name":  "returnTrue",
    "data":           {"int": "NULL"},
    "parents":        []
  },
  {
    "name":           ["level_number", "0"],
    "nexts":          [],
    "start_children": [],
    "children":       [],
    "function_name":  "returnTrue",
    "data":           {"int": "0"},
    "parents":        []
  },
  {
    "name":           ["state_number", "0"],
    "nexts":          [],
    "start_children": [],
    "children":       [],
    "function_name":  "returnTrue",
    "data":           {"int": "0"},
    "parents":        []
  },
  {
    "name":           ["indent_number", "0", "76543"],
    "nexts":          [],
    "start_children": [],
    "children":       [],
    "function_name":  "returnTrue",
    "data":           {"int": "0"},
    "parents":        []
  },
    
  {
    "name":           ["max_stack_index"],
    "nexts":          [],
    "start_children": [],
    "children":       [],
    "function_name":  "returnTrue",
    "data":           {"int": "0"},
    "parents":        []
  },
  {
    "name":           ["i"],
    "nexts":          [],
    "start_children": [],
    "children":       [],
    "function_name":  "returnTrue",
    "data":           {"int": "0"},
    "parents":        []
  },
  {
    "name":           ["what_is_current_word_to_pre_word"],
    "nexts":          [],
    "start_children": [["child", "nexts"],
                       ["sibling"],
                       ["new_parent"]],
    "children":       [],
    "function_name":  "returnTrue",
    "data":           {},
    "parents":        []
  },
    {
    "name":           ["states", "state"],
    "nexts":          [],
    "start_children": [],
    "children":       [],
    "function_name":  "returnTrue",
    "data":           {},
    "parents":        []
  }
  {
    "name":           ["states", "state"],
    "nexts":          [["one name"]],
    "start_children": [["child", "nexts"],
                       ["sibling"],
                       ["new_parent"]],
    "children":       [["a child"], ["another child"]],
    "function_name":  "returnTrue",
    "data":           {"int": "0"},
    "parents":        [["root"], ["0"]]
  }
]